MANIFEST.in
README.md
setup.py
pybraincompare/__init__.py
pybraincompare.egg-info/PKG-INFO
pybraincompare.egg-info/SOURCES.txt
pybraincompare.egg-info/dependency_links.txt
pybraincompare.egg-info/pbr.json
pybraincompare.egg-info/requires.txt
pybraincompare.egg-info/top_level.txt
pybraincompare/compare/__init__.py
pybraincompare/compare/atlas.py
pybraincompare/compare/maths.py
pybraincompare/compare/mrutils.py
pybraincompare/compare/network.py
pybraincompare/compare/scatterplot.py
pybraincompare/compare/search.py
pybraincompare/mr/2mm16_zstat1_1.nii
pybraincompare/mr/2mm16_zstat3_1.nii
pybraincompare/mr/8mm16_zstat1_1.nii
pybraincompare/mr/8mm16_zstat3_1.nii
pybraincompare/mr/MNI-maxprob-thr25-2mm.nii
pybraincompare/mr/MNI-maxprob-thr25-8mm.nii
pybraincompare/mr/MNI.xml
pybraincompare/mr/MNI152_T1_2mm_brain.nii.gz
pybraincompare/mr/MNI152_T1_2mm_brain_mask.nii.gz
pybraincompare/mr/MNI152_T1_4mm_brain.nii.gz
pybraincompare/mr/MNI152_T1_4mm_brain_mask.nii.gz
pybraincompare/mr/MNI152_T1_8mm_brain_mask.nii.gz
pybraincompare/mr/__init__.py
pybraincompare/mr/datasets.py
pybraincompare/mr/transformation.py
pybraincompare/ontology/__init__.py
pybraincompare/ontology/export.py
pybraincompare/ontology/graph.py
pybraincompare/ontology/inference.py
pybraincompare/ontology/tree.py
pybraincompare/report/__init__.py
pybraincompare/report/animate.py
pybraincompare/report/colors.py
pybraincompare/report/histogram.py
pybraincompare/report/image.py
pybraincompare/report/qa.py
pybraincompare/report/webreport.py
pybraincompare/template/__init__.py
pybraincompare/template/futils.py
pybraincompare/template/templates.py
pybraincompare/template/visual.py
pybraincompare/template/css/prettyPhoto.css
pybraincompare/template/html/brainglass_interface.html
pybraincompare/template/html/connectogram.html
pybraincompare/template/html/histogram.html
pybraincompare/template/html/ontology_tree.html
pybraincompare/template/html/qa_alerts.html
pybraincompare/template/html/qa_histograms.html
pybraincompare/template/html/qa_index.html
pybraincompare/template/html/qa_single_statmap.html
pybraincompare/template/html/qa_single_statmap_mean.html
pybraincompare/template/html/qa_summary_table.html
