Metadata-Version: 1.0
Name: pybraincompare
Version: 0.1.19
Summary: meta analysis and comparison for neuroimaging in python
Home-page: http://www.github.com/vsoch/pybraincompare
Author: Vanessa Sochat
Author-email: vsochat@stanford.edu
License: LICENSE.txt
Platform: UNKNOWN
